setup.py
src/txCascil/__init__.py
src/txCascil/events.py
src/txCascil/exceptions.py
src/txCascil/registry_manager.py
src/txCascil.egg-info/PKG-INFO
src/txCascil.egg-info/SOURCES.txt
src/txCascil.egg-info/dependency_links.txt
src/txCascil.egg-info/requires.txt
src/txCascil.egg-info/top_level.txt
src/txCascil/client/__init__.py
src/txCascil/client/authentication_controller_factory.py
src/txCascil/client/client_controller.py
src/txCascil/client/client_controller_factory.py
src/txCascil/client/protocol_factory.py
src/txCascil/client/service.py
src/txCascil/client/service_factory.py
src/txCascil/client/authentication_controllers/__init__.py
src/txCascil/client/authentication_controllers/cube2crypto.py
src/txCascil/packings/__init__.py
src/txCascil/packings/edn.py
src/txCascil/packings/json.py
src/txCascil/permissions/__init__.py
src/txCascil/permissions/functionality.py
src/txCascil/permissions/group.py
src/txCascil/permissions/permission_resolver.py
src/txCascil/server/__init__.py
src/txCascil/server/authentication_controller_factory.py
src/txCascil/server/central_message_handler.py
src/txCascil/server/client_controller.py
src/txCascil/server/client_controller_factory.py
src/txCascil/server/protocol_factory.py
src/txCascil/server/service.py
src/txCascil/server/service_factory.py
src/txCascil/server/authentication_controllers/__init__.py
src/txCascil/server/authentication_controllers/cube2crypto.py
src/txCascil/transports/__init__.py
src/txCascil/transports/netstring.py
src/txCascil/utils/__init__.py
src/txCascil/utils/enum.py
src/txCascil/utils/import_all.py