Metadata-Version: 1.1
Name: txCascil
Version: 0.1
Summary: (Twisted) Cube Ancillary Service Communication Interface Layer
Home-page: https://github.com/fdChasm/txCascil
Author: Chasm
Author-email: fd.chasm@gmail.com
License: MIT
Platform: UNKNOWN
Classifier: Development Status :: 3 - Alpha
Classifier: Topic :: Software Development :: Libraries :: Python Modules
Classifier: License :: OSI Approved :: MIT License
Classifier: Natural Language :: English
